rmsgd/__init__.py
rmsgd/components.py
rmsgd/matrix_factorization.py
rmsgd/metrics.py
rmsgd/rmsgd.py
rmsgd-1.0.2.dist-info/LICENSE
rmsgd-1.0.2.dist-info/METADATA
rmsgd-1.0.2.dist-info/WHEEL
rmsgd-1.0.2.dist-info/top_level.txt
rmsgd-1.0.2.dist-info/RECORD
