Metadata-Version: 2.1
Name: rmsgd
Version: 1.0.2
Summary: Python package for RMSGD
Home-page: https://github.com/mahdihosseini/RMSGD
Author: Mahdi Hosseini and Mathieu Tuli
Author-email: mahdi.hosseini@mail.utoronto.ca
License: License :: Other/Proprietary License
Project-URL: Bug Tracker, https://github.com/mahdihosseini/RMSGD/issues
Platform: UNKNOWN
Classifier: Development Status :: 4 - Beta
Classifier: Intended Audience :: Developers
Classifier: Intended Audience :: Science/Research
Classifier: License :: Other/Proprietary License
Classifier: Topic :: Scientific/Engineering :: Artificial Intelligence
Classifier: Programming Language :: Python :: 3
Requires-Python: >=3.6
License-File: LICENSE
Requires-Dist: numpy (>=1.20.2)
Requires-Dist: scipy (>=1.6.2)
Requires-Dist: torch (>=1.8.1)
Provides-Extra: docs
Requires-Dist: sphinx ; extra == 'docs'
Requires-Dist: sphinx-rtd-theme ; extra == 'docs'
Requires-Dist: recommonmark ; extra == 'docs'
